factorial_bombom2108/__init__.py
factorial_bombom2108/app.py
factorial_bombom2108/factorial.py
factorial_bombom2108-0.1.0.dist-info/METADATA
factorial_bombom2108-0.1.0.dist-info/WHEEL
factorial_bombom2108-0.1.0.dist-info/RECORD
